package_name/__init__.py
package_name/file1_name.py
package_name/file2_name.py
kauateotonio_package-0.1.0.dist-info/METADATA
kauateotonio_package-0.1.0.dist-info/WHEEL
kauateotonio_package-0.1.0.dist-info/top_level.txt
kauateotonio_package-0.1.0.dist-info/RECORD
